_pycapsicum.c
pycapsicum.py
setup.py
pycapsicum.egg-info/PKG-INFO
pycapsicum.egg-info/SOURCES.txt
pycapsicum.egg-info/dependency_links.txt
pycapsicum.egg-info/top_level.txt