Metadata-Version: 1.0
Name: pycapsicum
Version: 1.0
Summary: python interface to capsicum security
Home-page: UNKNOWN
Author: Chris Stillson
Author-email: stillson@gmail.com
License: New BSD license
Platform: UNKNOWN
